rfviser/__init__.py
rfviser/_client_autobuild.py
rfviser/_gui_api.py
rfviser/_gui_handles.py
rfviser/_icons.py
rfviser/_icons_enum.py
rfviser/_icons_enum.pyi
rfviser/_icons_generate_enum.py
rfviser/_messages.py
rfviser/_notification_handle.py
rfviser/_scene_api.py
rfviser/_scene_handles.py
rfviser/_threadpool_exceptions.py
rfviser/_tunnel.py
rfviser/_viser.py
rfviser/py.typed
rfviser/_icons/tabler-icons.zip
rfviser/client/.eslintrc.js
rfviser/client/.gitignore
rfviser/client/index.html
rfviser/client/package.json
rfviser/client/postcss.config.cjs
rfviser/client/tsconfig.json
rfviser/client/vite-env.d.ts
rfviser/client/vite.config.mts
rfviser/client/yarn.lock
"rfviser/client/build/Inter-VariableFont_slnt,wght.ttf"
rfviser/client/build/index.html
rfviser/client/build/logo.svg
rfviser/client/build/manifest.json
rfviser/client/build/robots.txt
rfviser/client/build/assets/Sorter-Df0J3ZWJ.wasm
rfviser/client/build/assets/SplatSortWorker-D00osGmu.js
rfviser/client/build/assets/WebsocketServerWorker-CfOJfyVX.js
rfviser/client/build/assets/__vite-browser-external-BIHI7g3E.js
rfviser/client/build/assets/index-D2f7UuRj.js
rfviser/client/build/assets/index-rDcZU3kF.css
rfviser/client/build/hdri/dikhololo_night_1k.hdr
rfviser/client/build/hdri/empty_warehouse_01_1k.hdr
rfviser/client/build/hdri/forest_slope_1k.hdr
rfviser/client/build/hdri/kiara_1_dawn_1k.hdr
rfviser/client/build/hdri/lebombo_1k.hdr
rfviser/client/build/hdri/potsdamer_platz_1k.hdr
rfviser/client/build/hdri/rooitou_park_1k.hdr
rfviser/client/build/hdri/st_fagans_interior_1k.hdr
rfviser/client/build/hdri/studio_small_03_1k.hdr
rfviser/client/build/hdri/venice_sunset_1k.hdr
"rfviser/client/public/Inter-VariableFont_slnt,wght.ttf"
rfviser/client/public/logo.svg
rfviser/client/public/manifest.json
rfviser/client/public/robots.txt
rfviser/client/public/hdri/dikhololo_night_1k.hdr
rfviser/client/public/hdri/empty_warehouse_01_1k.hdr
rfviser/client/public/hdri/forest_slope_1k.hdr
rfviser-0.2.23.dist-info/METADATA
rfviser-0.2.23.dist-info/WHEEL
rfviser-0.2.23.dist-info/entry_points.txt
rfviser-0.2.23.dist-info/licenses/LICENSE
rfviser-0.2.23.dist-info/RECORD
