Metadata-Version: 2.4
Name: rfviser
Version: 0.2.23
Summary: 3D visualization + Python
Project-URL: GitHub, https://github.com/nerfstudio-project/viser
License: MIT
License-File: LICENSE
Classifier: License :: OSI Approved :: MIT License
Classifier: Operating System :: OS Independent
Classifier: Programming Language :: Python :: 3
Classifier: Programming Language :: Python :: 3.8
Classifier: Programming Language :: Python :: 3.9
Classifier: Programming Language :: Python :: 3.10
Classifier: Programming Language :: Python :: 3.11
Classifier: Programming Language :: Python :: 3.12
Requires-Python: >=3.8
Requires-Dist: imageio>=2.0.0
Requires-Dist: msgspec>=0.18.6
Requires-Dist: nodeenv>=1.8.0
Requires-Dist: numpy>=1.0.0
Requires-Dist: plyfile>=1.0.2
Requires-Dist: psutil>=5.9.5
Requires-Dist: rich>=13.3.3
Requires-Dist: scikit-image>=0.18.0
Requires-Dist: scipy>=1.7.3
Requires-Dist: tqdm>=4.0.0
Requires-Dist: trimesh>=3.21.7
Requires-Dist: tyro>=0.2.0
Requires-Dist: websockets>=13.1
Requires-Dist: yourdfpy>=0.0.53
Provides-Extra: dev
Requires-Dist: hypothesis[numpy]; extra == 'dev'
Requires-Dist: pre-commit==3.3.2; extra == 'dev'
Requires-Dist: pyright>=1.1.308; extra == 'dev'
Requires-Dist: pytest; extra == 'dev'
Requires-Dist: ruff>=0.9.3; extra == 'dev'
Provides-Extra: examples
Requires-Dist: gdown>=4.6.6; extra == 'examples'
Requires-Dist: matplotlib>=3.7.1; extra == 'examples'
Requires-Dist: opencv-python; extra == 'examples'
Requires-Dist: plotly>=5.21.0; extra == 'examples'
Requires-Dist: plyfile; extra == 'examples'
Requires-Dist: pyliblzfse>=0.4.1; (platform_system != 'Windows') and extra == 'examples'
Requires-Dist: robot-descriptions>=1.10.0; extra == 'examples'
Requires-Dist: torch>=1.13.1; extra == 'examples'
